vocr/__init__.py
vocr/__main__.py
vocr/cli.py
vocr/gui.py
vocr/py.typed
vocr/vocr.py
vocr/res/__init__.py
vocr/res/vocr.ico
vocr-0.3.0.dist-info/METADATA
vocr-0.3.0.dist-info/WHEEL
vocr-0.3.0.dist-info/entry_points.txt
vocr-0.3.0.dist-info/licenses/LICENSE
vocr-0.3.0.dist-info/RECORD
