Metadata-Version: 2.1
Name: vocr
Version: 0.3.0
Summary: Vietnamese OCR
Project-URL: Homepage, https://github.com/AbsoluteWinter/vocr
Project-URL: Repository, https://github.com/AbsoluteWinter/vocr
Project-URL: Issues, https://github.com/AbsoluteWinter/vocr/issues
Author: AbsoluteWinter
License: MIT License
License-File: LICENSE
Classifier: License :: OSI Approved :: MIT License
Classifier: Natural Language :: English
Classifier: Operating System :: OS Independent
Classifier: Programming Language :: Python :: 3
Classifier: Programming Language :: Python :: 3 :: Only
Classifier: Programming Language :: Python :: 3.8
Classifier: Programming Language :: Python :: 3.9
Classifier: Programming Language :: Python :: 3.10
Classifier: Programming Language :: Python :: 3.11
Classifier: Programming Language :: Python :: 3.12
Requires-Python: <4,>=3.8
Requires-Dist: click>=8.0.0
Requires-Dist: customtkinter
Requires-Dist: importlib-resources; python_version < '3.10'
Requires-Dist: joblib
Requires-Dist: opencv-python
Requires-Dist: pillow
Requires-Dist: pytesseract
Requires-Dist: tqdm
Provides-Extra: dev
Requires-Dist: hatch; extra == 'dev'
Requires-Dist: pytest>=7.0.0; extra == 'dev'
